pygraphprofiler/__init__.py
pygraphprofiler/profiler.py
pygraphprofiler/utils/__init__.py
pygraphprofiler/utils/graph.py
pygraphprofiler/utils/plot.py
pygraphprofiler/utils/scc.py
pygraphprofiler-0.1.9.dist-info/METADATA
pygraphprofiler-0.1.9.dist-info/WHEEL
pygraphprofiler-0.1.9.dist-info/top_level.txt
pygraphprofiler-0.1.9.dist-info/RECORD
