Metadata-Version: 2.1
Name: pygraphprofiler
Version: 0.1.9
Summary: A Python package for profiling functions.
Home-page: https://github.com/adamvis/pygraphprofiler
Author: Adam Viscusi
Author-email: adam.viscusi@gmail.com
License: UNKNOWN
Platform: UNKNOWN
Classifier: Programming Language :: Python :: 3
Classifier: License :: OSI Approved :: MIT License
Classifier: Operating System :: OS Independent
Requires-Python: >=3.6
Requires-Dist: matplotlib (>=3.5.1)
Requires-Dist: networkx (>=3.0)
Requires-Dist: pandas (>=1.4.0)
Requires-Dist: pygraphviz (>=1.10)
